.gitignore
.pre-commit-config.yaml
LICENSE.md
README.md
pyproject.toml
setup.py
.github/workflows/ci.yml
.github/workflows/pypi.yml
nbclick/__init__.py
nbclick/__main__.py
nbclick/_version.py
nbclick.egg-info/PKG-INFO
nbclick.egg-info/SOURCES.txt
nbclick.egg-info/dependency_links.txt
nbclick.egg-info/entry_points.txt
nbclick.egg-info/requires.txt
nbclick.egg-info/top_level.txt
test/test_cli.py
test/notebooks/boolean.ipynb
test/notebooks/hetlist.ipynb
test/notebooks/integer.ipynb
test/notebooks/list.ipynb
test/notebooks/noparams.ipynb
test/notebooks/string.ipynb