Metadata-Version: 2.1
Name: nbclick
Version: 0.4.1
Summary: Modify and run Jupyter notebooks from the command line
Maintainer-email: Dominic Kempf <ssc@iwr.uni-heidelberg.de>
License: MIT
Classifier: License :: OSI Approved :: MIT License
Classifier: Operating System :: OS Independent
Classifier: Programming Language :: Python :: 3
Provides-Extra: tests
License-File: LICENSE.md
